LICENSE.txt
MANIFEST.in
NEWS.txt
README.rst
issue_template.md
pull_request_template.md
pyproject.toml
setup.cfg
setup.py
test_requirements.txt
examples/batch-mdq-loop.fd
examples/big.fd
examples/big.xrd
examples/dj.fd
examples/edugain-copy.fd
examples/edugain-fork-and-filter.fd
examples/edugain-fork.fd
examples/edugain-idps.fd
examples/edugain-json.fd
examples/edugain-mdq.fd
examples/edugain.fd
examples/eidas.fd
examples/expiration.fd
examples/filter-idps.fd
examples/kirei2.fd
examples/links.xrd
examples/load.fd
examples/mdx.fd
examples/ndn-links.xrd
examples/ndn.fd
examples/new-renater.fd
examples/out-edugain.fd
examples/p11.fd
examples/pp.fd
examples/renater.fd
examples/safire-fed.fd
examples/test.fd
examples/uk.fd
examples/ukmulti.fd
scripts/mirror-mdq.sh
src/pyFF.egg-info/PKG-INFO
src/pyFF.egg-info/SOURCES.txt
src/pyFF.egg-info/dependency_links.txt
src/pyFF.egg-info/entry_points.txt
src/pyFF.egg-info/not-zip-safe
src/pyFF.egg-info/requires.txt
src/pyFF.egg-info/top_level.txt
src/pyff/__init__.py
src/pyff/api.py
src/pyff/builtins.py
src/pyff/constants.py
src/pyff/decorators.py
src/pyff/exceptions.py
src/pyff/fetch.py
src/pyff/locks.py
src/pyff/logs.py
src/pyff/md.py
src/pyff/mdq.py
src/pyff/merge_strategies.py
src/pyff/parse.py
src/pyff/pipes.py
src/pyff/repo.py
src/pyff/resource.py
src/pyff/samlmd.py
src/pyff/store.py
src/pyff/tools.py
src/pyff/utils.py
src/pyff/wsgi.py
src/pyff/schema/MetadataExchange.xsd
src/pyff/schema/XMLSchema.xsd
src/pyff/schema/atom.xsd
src/pyff/schema/cs-sstc-schema-assertion-1.1.xsd
src/pyff/schema/oasis-200401-wss-wssecurity-secext-1.0.xsd
src/pyff/schema/oasis-200401-wss-wssecurity-utility-1.0.xsd
src/pyff/schema/privacy.xsd
src/pyff/schema/saml-metadata-rpi-v1.0.xsd
src/pyff/schema/saml-metadata-trustinfo-v1.0.xsd
src/pyff/schema/saml-schema-assertion-2.0.xsd
src/pyff/schema/saml-schema-metadata-2.0.xsd
src/pyff/schema/saml-schema-protocol-2.0.xsd
src/pyff/schema/schema.xsd
src/pyff/schema/shibboleth-metadata-1.0.xsd
src/pyff/schema/shibboleth-trust-1.0.xsd
src/pyff/schema/shibboleth.xsd
src/pyff/schema/sstc-metadata-attr.xsd
src/pyff/schema/sstc-saml-idp-discovery.xsd
src/pyff/schema/sstc-saml-metadata-algsupport.xsd
