Metadata-Version: 2.4
Name: pyFF
Version: 2.1.4
Summary: Federation Feeder
Home-page: https://pyff.io
Author: Enrique Pérez Arnaud
Author-email: Leif Johansson <leifj@sunet.se>, Fredrik Thulin <redrik@thulin.net>, Mikael Frykholm <mifr@sunet.se>
Maintainer-email: Mikael Frykholm <mifr@sunet.se>
Requires-Python: >=3.7
License-File: LICENSE.txt
Requires-Dist: accept-types>=0.4.1
Requires-Dist: apscheduler==3.6.3
Requires-Dist: cachetools>=5.5.2
Requires-Dist: eval-type-backport>=0.2.2; python_full_version == "3.9.*"
Requires-Dist: gunicorn>=23.0.0
Requires-Dist: httplib2>=0.7.7
Requires-Dist: lxml>=4.1.1
Requires-Dist: mako>=1.3.10
Requires-Dist: pyconfig>=3.2.3
Requires-Dist: pydantic>=2.8
Requires-Dist: pyramid>=2.0.2
Requires-Dist: pytz>=2025.2
Requires-Dist: pyxmlsecurity>=1.0.0
Requires-Dist: pyyaml>=3.10
Requires-Dist: redis>=5.3.0
Requires-Dist: redis-collections>=0.13.0
Requires-Dist: requests>=2.32.3
Requires-Dist: requests-cache>=1.2.1
Requires-Dist: requests-file>=2.1.0
Requires-Dist: setuptools>=78.1.1
Requires-Dist: simplejson>=2.6.2
Requires-Dist: str2bool>=1.1
Requires-Dist: urllib3==1.26.19
Requires-Dist: whoosh>=2.7.4
Requires-Dist: wsgi-intercept>=1.13.1
Requires-Dist: xmldiff>=2.7.0
Requires-Dist: zipp>=3.19.1
Dynamic: home-page
Dynamic: license-file
Dynamic: requires-python
